hue_snek_pkg/__init__.py
hue_snek_pkg/hue_snek.py
hue_snek_channel42-0.3.dist-info/LICENSE
hue_snek_channel42-0.3.dist-info/METADATA
hue_snek_channel42-0.3.dist-info/WHEEL
hue_snek_channel42-0.3.dist-info/top_level.txt
hue_snek_channel42-0.3.dist-info/RECORD
