Metadata-Version: 2.1
Name: hue-snek-channel42
Version: 0.3
Summary: A library for the Philips Hue API
Home-page: https://github.com/channel-42/hue-snek
Author: Channel 42
Author-email: 
License: UNKNOWN
Platform: UNKNOWN
Classifier: Programming Language :: Python :: 3
Classifier: License :: OSI Approved :: MIT License
Classifier: Operating System :: OS Independent
Requires-Dist: urllib3
